Metadata-Version: 2.4
Name: hack4u-07-2025
Version: 0.1.0
Summary: Biblioteca Hack4u para busquedas
Author: sergiobrvo01
License: MIT
Classifier: Programming Language :: Python :: 3
Classifier: License :: OSI Approved :: MIT License
Classifier: Operating System :: OS Independent
Requires-Python: >=3.6
Dynamic: author
Dynamic: classifier
Dynamic: description
Dynamic: description-content-type
Dynamic: license
Dynamic: requires-python
Dynamic: summary
